alita_sdk/__init__.py
alita_sdk/cli/__init__.py
alita_sdk/cli/__main__.py
alita_sdk/cli/agent_executor.py
alita_sdk/cli/agent_loader.py
alita_sdk/cli/agent_ui.py
alita_sdk/cli/agents.py
alita_sdk/cli/callbacks.py
alita_sdk/cli/cli.py
alita_sdk/cli/config.py
alita_sdk/cli/formatting.py
alita_sdk/cli/input_handler.py
alita_sdk/cli/inventory.py
alita_sdk/cli/mcp_loader.py
alita_sdk/cli/toolkit.py
alita_sdk/cli/toolkit_loader.py
alita_sdk/cli/agent/__init__.py
alita_sdk/cli/agent/default.py
alita_sdk/cli/context/__init__.py
alita_sdk/cli/context/cleanup.py
alita_sdk/cli/context/manager.py
alita_sdk/cli/context/message.py
alita_sdk/cli/context/strategies.py
alita_sdk/cli/context/token_estimation.py
alita_sdk/cli/testcases/__init__.py
alita_sdk/cli/testcases/data_generation.py
alita_sdk/cli/testcases/discovery.py
alita_sdk/cli/testcases/executor.py
alita_sdk/cli/testcases/logger.py
alita_sdk/cli/testcases/parser.py
alita_sdk/cli/testcases/prompts.py
alita_sdk/cli/testcases/reporting.py
alita_sdk/cli/testcases/setup.py
alita_sdk/cli/testcases/test_runner.py
alita_sdk/cli/testcases/utils.py
alita_sdk/cli/testcases/validation.py
alita_sdk/cli/testcases/workflow.py
alita_sdk/cli/tools/__init__.py
alita_sdk/cli/tools/approval.py
alita_sdk/cli/tools/filesystem.py
alita_sdk/cli/tools/planning.py
alita_sdk/cli/tools/terminal.py
alita_sdk/community/__init__.py
alita_sdk/community/utils.py
alita_sdk/community/inventory/__init__.py
alita_sdk/community/inventory/config.py
alita_sdk/community/inventory/enrichment.py
alita_sdk/community/inventory/extractors.py
alita_sdk/community/inventory/ingestion.py
alita_sdk/community/inventory/knowledge_graph.py
alita_sdk/community/inventory/presets.py
alita_sdk/community/inventory/retrieval.py
alita_sdk/community/inventory/toolkit.py
alita_sdk/community/inventory/toolkit_utils.py
alita_sdk/community/inventory/visualize.py
alita_sdk/community/inventory/parsers/__init__.py
alita_sdk/community/inventory/parsers/base.py
alita_sdk-0.3.650.dist-info/licenses/LICENSE
alita_sdk-0.3.650.dist-info/METADATA
alita_sdk-0.3.650.dist-info/WHEEL
alita_sdk-0.3.650.dist-info/entry_points.txt
alita_sdk-0.3.650.dist-info/top_level.txt
alita_sdk-0.3.650.dist-info/RECORD
