Metadata-Version: 2.4
Name: alita_sdk
Version: 0.3.650
Summary: SDK for building langchain agents using resources from Alita
Author-email: Artem Rozumenko <artyom.rozumenko@gmail.com>, Mikalai Biazruchka <mikalai_biazruchka@epam.com>, Roman Mitusov <roman_mitusov@epam.com>, Ivan Krakhmaliuk <lifedj27@gmail.com>, Artem Dubrovskiy <ad13box@gmail.com>
License-Expression: Apache-2.0
Project-URL: Homepage, https://projectalita.ai
Project-URL: Issues, https://github.com/ProjectAlita/alita-sdk/issues
Classifier: Programming Language :: Python :: 3
Classifier: Operating System :: OS Independent
Requires-Python: >=3.10
License-File: LICENSE
Requires-Dist: sqlalchemy<2.0.36
Requires-Dist: tiktoken>=0.7.0
Requires-Dist: openai>=1.55.0
Requires-Dist: python-dotenv~=1.0.1
Requires-Dist: jinja2~=3.1.3
Requires-Dist: pillow~=11.1.0
Requires-Dist: requests~=2.3
Requires-Dist: pydantic~=2.12.0
Requires-Dist: chardet==5.2.0
Requires-Dist: fastapi==0.115.9
Requires-Dist: httpcore==1.0.7
Requires-Dist: urllib3>=2
Requires-Dist: certifi==2024.8.30
Requires-Dist: aiohttp>=3.9.0
Provides-Extra: runtime
Requires-Dist: langchain-core==1.2.7; extra == "runtime"
Requires-Dist: langchain==1.2.6; extra == "runtime"
Requires-Dist: langchain-community==0.4.1; extra == "runtime"
Requires-Dist: langchain-openai==1.1.7; extra == "runtime"
Requires-Dist: langchain-anthropic==1.3.1; extra == "runtime"
Requires-Dist: langchain-text-splitters==1.1.0; extra == "runtime"
Requires-Dist: langchain-chroma==1.0.0; extra == "runtime"
Requires-Dist: langchain-unstructured==1.0.0; extra == "runtime"
Requires-Dist: langchain-postgres==0.0.16; extra == "runtime"
Requires-Dist: langchain-mcp-adapters<0.2.0,>=0.1.14; extra == "runtime"
Requires-Dist: langgraph==1.0.7; extra == "runtime"
Requires-Dist: langgraph-prebuilt==1.0.7; extra == "runtime"
Requires-Dist: langgraph-swarm==0.1.0; extra == "runtime"
Requires-Dist: langgraph-checkpoint==2.1.2; extra == "runtime"
Requires-Dist: langgraph-checkpoint-sqlite==2.0.11; extra == "runtime"
Requires-Dist: langgraph-checkpoint-postgres==2.0.21; extra == "runtime"
Requires-Dist: langsmith>=0.3.45; extra == "runtime"
Requires-Dist: anthropic==0.76.0; extra == "runtime"
Requires-Dist: chromadb<2.0.0,>=1.0.20; extra == "runtime"
Requires-Dist: pgvector==0.2.5; extra == "runtime"
Requires-Dist: unstructured[local-inference]==0.16.23; extra == "runtime"
Requires-Dist: unstructured_pytesseract==0.3.13; extra == "runtime"
Requires-Dist: unstructured_inference==0.8.7; extra == "runtime"
Requires-Dist: python-pptx==1.0.2; extra == "runtime"
Requires-Dist: python-docx==1.1.2; extra == "runtime"
Requires-Dist: openpyxl==3.1.2; extra == "runtime"
Requires-Dist: pypdf==4.3.1; extra == "runtime"
Requires-Dist: pdfminer.six==20240706; extra == "runtime"
Requires-Dist: pdf2image==1.16.3; extra == "runtime"
Requires-Dist: pikepdf==8.7.1; extra == "runtime"
Requires-Dist: docx2txt==0.8; extra == "runtime"
Requires-Dist: mammoth==1.9.0; extra == "runtime"
Requires-Dist: reportlab==4.2.5; extra == "runtime"
Requires-Dist: svglib==1.5.1; extra == "runtime"
Requires-Dist: cairocffi==1.7.1; extra == "runtime"
Requires-Dist: rlpycairo==0.3.0; extra == "runtime"
Requires-Dist: keybert==0.8.3; extra == "runtime"
Requires-Dist: sentence-transformers==2.7.0; extra == "runtime"
Requires-Dist: gensim==4.3.3; extra == "runtime"
Requires-Dist: scipy==1.13.1; extra == "runtime"
Requires-Dist: opencv-python==4.11.0.86; extra == "runtime"
Requires-Dist: pytesseract==0.3.13; extra == "runtime"
Requires-Dist: markdown==3.5.1; extra == "runtime"
Requires-Dist: beautifulsoup4==4.12.2; extra == "runtime"
Requires-Dist: charset_normalizer==3.3.2; extra == "runtime"
Requires-Dist: opentelemetry-exporter-otlp-proto-grpc>=1.25.0; extra == "runtime"
Requires-Dist: opentelemetry_api>=1.25.0; extra == "runtime"
Requires-Dist: opentelemetry_instrumentation>=0.46b0; extra == "runtime"
Requires-Dist: grpcio_status>=1.63.0rc1; extra == "runtime"
Requires-Dist: protobuf>=4.25.7; extra == "runtime"
Requires-Dist: streamlit>=1.28.0; extra == "runtime"
Provides-Extra: tools
Requires-Dist: dulwich==0.21.6; extra == "tools"
Requires-Dist: paramiko==3.3.1; extra == "tools"
Requires-Dist: pygithub==2.3.0; extra == "tools"
Requires-Dist: python-gitlab==4.5.0; extra == "tools"
Requires-Dist: gitpython==3.1.43; extra == "tools"
Requires-Dist: atlassian-python-api~=4.0.7; extra == "tools"
Requires-Dist: jira==3.8.0; extra == "tools"
Requires-Dist: qtest-swagger-client==0.0.3; extra == "tools"
Requires-Dist: testrail-api==1.13.4; extra == "tools"
Requires-Dist: zephyr-python-api==0.1.0; extra == "tools"
Requires-Dist: azure-devops==7.1.0b4; extra == "tools"
Requires-Dist: azure-core==1.30.2; extra == "tools"
Requires-Dist: azure-identity==1.16.0; extra == "tools"
Requires-Dist: azure-keyvault-keys==4.9.0; extra == "tools"
Requires-Dist: azure-keyvault-secrets==4.8.0; extra == "tools"
Requires-Dist: azure-mgmt-core==1.4.0; extra == "tools"
Requires-Dist: azure-mgmt-resource==23.0.1; extra == "tools"
Requires-Dist: azure-mgmt-storage==21.1.0; extra == "tools"
Requires-Dist: azure-storage-blob==12.23.1; extra == "tools"
Requires-Dist: azure-search-documents==11.5.2; extra == "tools"
Requires-Dist: msrest==0.7.1; extra == "tools"
Requires-Dist: boto3>=1.37.23; extra == "tools"
Requires-Dist: PyMySQL==1.1.1; extra == "tools"
Requires-Dist: psycopg2-binary==2.9.10; extra == "tools"
Requires-Dist: Office365-REST-Python-Client==2.5.14; extra == "tools"
Requires-Dist: pypdf2~=3.0.1; extra == "tools"
Requires-Dist: FigmaPy==2018.1.0; extra == "tools"
Requires-Dist: pandas==2.2.3; extra == "tools"
Requires-Dist: factor_analyzer==0.5.1; extra == "tools"
Requires-Dist: statsmodels==0.14.4; extra == "tools"
Requires-Dist: tabulate==0.9.0; extra == "tools"
Requires-Dist: tree_sitter==0.20.2; extra == "tools"
Requires-Dist: tree-sitter-languages==1.10.2; extra == "tools"
Requires-Dist: astor~=0.8.1; extra == "tools"
Requires-Dist: markdownify~=1.1.0; extra == "tools"
Requires-Dist: requests_openapi==1.0.5; extra == "tools"
Requires-Dist: duckduckgo_search==5.3.0; extra == "tools"
Requires-Dist: playwright>=1.52.0; extra == "tools"
Requires-Dist: google-api-python-client==2.154.0; extra == "tools"
Requires-Dist: wikipedia==1.4.0; extra == "tools"
Requires-Dist: lxml==5.2.2; extra == "tools"
Requires-Dist: python-graphql-client~=0.4.3; extra == "tools"
Requires-Dist: pymupdf==1.24.9; extra == "tools"
Requires-Dist: googlemaps==4.10.0; extra == "tools"
Requires-Dist: yagmail==0.15.293; extra == "tools"
Requires-Dist: pysnc==1.1.10; extra == "tools"
Requires-Dist: pyral==1.6.0; extra == "tools"
Requires-Dist: shortuuid==1.0.13; extra == "tools"
Requires-Dist: yarl==1.17.1; extra == "tools"
Requires-Dist: langmem==0.0.27; extra == "tools"
Requires-Dist: textract-py3==2.1.1; extra == "tools"
Requires-Dist: slack_sdk==3.35.0; extra == "tools"
Requires-Dist: deltalake==1.0.2; extra == "tools"
Requires-Dist: google_cloud_bigquery==3.34.0; extra == "tools"
Requires-Dist: python-calamine==0.5.3; extra == "tools"
Provides-Extra: community
Requires-Dist: retry-extended==0.2.3; extra == "community"
Requires-Dist: pyobjtojson==0.3; extra == "community"
Requires-Dist: elitea-analyse==0.1.2; extra == "community"
Requires-Dist: networkx>=3.0; extra == "community"
Provides-Extra: all
Requires-Dist: alita-sdk[runtime]; extra == "all"
Requires-Dist: alita-sdk[tools]; extra == "all"
Requires-Dist: alita-sdk[community]; extra == "all"
Provides-Extra: dev
Requires-Dist: pytest; extra == "dev"
Requires-Dist: pytest-cov; extra == "dev"
Requires-Dist: black; extra == "dev"
Requires-Dist: flake8; extra == "dev"
Requires-Dist: mypy; extra == "dev"
Provides-Extra: cli
Requires-Dist: click>=8.1.0; extra == "cli"
Requires-Dist: rich>=13.0.0; extra == "cli"
Requires-Dist: pyyaml>=6.0; extra == "cli"
Requires-Dist: langchain-mcp-adapters; extra == "cli"
Dynamic: license-file
